{
    "total":8,
    "items":[
        {
            "item_number":"8001152",
            "name":"XM Test RE-XM0302",
            "object_type":"TRUCK_ITEM",
            "wonder_info":{
                "recipe_version_id":"800115201",
                "ingredient_id":null,
                "name":"RE-XM0302"
            },
            "related_wonder_infos":[

            ],
            "status":"BOM_CREATED",
            "restaurants":[
                {
                    "id":"0bebb8ce-9dbc-49eb-bbc4-aacc7d699cad",
                    "name":"XM Test Automation Use ONLY"
                },
                {
                    "id":"38b07107-087f-4f31-b856-14e400fd0f8a",
                    "name":"XM Test Sushi Co"
                },
                {
                    "id":"0f0dd5a4-ce3d-4f7e-a039-326c34bf95e8",
                    "name":"XM Test Utopia Bagels"
                }
            ],
            "has_customization":true
        },
        {
            "item_number":"8001269",
            "name":"XM test xRe20",
            "object_type":"TRUCK_ITEM",
            "wonder_info":{
                "recipe_version_id":"800126901",
                "ingredient_id":null,
                "name":"xRe20"
            },
            "related_wonder_infos":[

            ],
            "status":"BOM_CREATED",
            "restaurants":[
                {
                    "id":"0bebb8ce-9dbc-49eb-bbc4-aacc7d699cad",
                    "name":"XM Test Automation Use ONLY"
                },
                {
                    "id":"38b07107-087f-4f31-b856-14e400fd0f8a",
                    "name":"XM Test Sushi Co"
                },
                {
                    "id":"0f0dd5a4-ce3d-4f7e-a039-326c34bf95e8",
                    "name":"XM Test Utopia Bagels"
                }
            ],
            "has_customization":false
        },
        {
            "item_number":"8801251",
            "name":"XM Test xRe20[kit]",
            "object_type":"PARTIAL_KIT_ITEM",
            "wonder_info":{
                "recipe_version_id":"800126901",
                "ingredient_id":null,
                "name":"xRe20"
            },
            "related_wonder_infos":[

            ],
            "status":"NEW",
            "restaurants":[
                {
                    "id":"0bebb8ce-9dbc-49eb-bbc4-aacc7d699cad",
                    "name":"XM Test Automation Use ONLY"
                },
                {
                    "id":"38b07107-087f-4f31-b856-14e400fd0f8a",
                    "name":"XM Test Sushi Co"
                },
                {
                    "id":"0f0dd5a4-ce3d-4f7e-a039-326c34bf95e8",
                    "name":"XM Test Utopia Bagels"
                }
            ],
            "has_customization":false
        },
        {
            "item_number":"8001150",
            "name":"COM-XM0301",
            "object_type":"COMMISSARY_OR_BULK_ITEM",
            "wonder_info":{
                "recipe_version_id":"800115001",
                "ingredient_id":null,
                "name":"COM-XM0301"
            },
            "related_wonder_infos":[

            ],
            "status":"NEW",
            "restaurants":[
                {
                    "id":"0bebb8ce-9dbc-49eb-bbc4-aacc7d699cad",
                    "name":"XM Test Automation Use ONLY"
                },
                {
                    "id":"60d96c30-a5c3-4703-a3da-aaaf8984a503",
                    "name":"XM Test  Regression QA"
                },
                {
                    "id":"38b07107-087f-4f31-b856-14e400fd0f8a",
                    "name":"XM Test Sushi Co"
                },
                {
                    "id":"0f0dd5a4-ce3d-4f7e-a039-326c34bf95e8",
                    "name":"XM Test Utopia Bagels"
                }
            ],
            "has_customization":false
        },
        {
            "item_number":"8001259",
            "name":"XM Test ReD(xm)",
            "object_type":"TRUCK_ITEM",
            "wonder_info":{
                "recipe_version_id":"800125901",
                "ingredient_id":null,
                "name":"ReD(xm)"
            },
            "related_wonder_infos":[

            ],
            "status":"BOM_CREATED",
            "restaurants":[
                {
                    "id":"60d96c30-a5c3-4703-a3da-aaaf8984a503",
                    "name":"XM Test  Regression QA"
                },
                {
                    "id":"0bebb8ce-9dbc-49eb-bbc4-aacc7d699cad",
                    "name":"XM Test Automation Use ONLY"
                },
                {
                    "id":"38b07107-087f-4f31-b856-14e400fd0f8a",
                    "name":"XM Test Sushi Co"
                },
                {
                    "id":"0f0dd5a4-ce3d-4f7e-a039-326c34bf95e8",
                    "name":"XM Test Utopia Bagels"
                }
            ],
            "has_customization":false
        },
        {
            "item_number":"8001267",
            "name":"XM Test ReH(xm)",
            "object_type":"TRUCK_ITEM",
            "wonder_info":{
                "recipe_version_id":"800126701",
                "ingredient_id":null,
                "name":"ReH(xm)"
            },
            "related_wonder_infos":[

            ],
            "status":"BOM_CREATED",
            "restaurants":[
                {
                    "id":"60d96c30-a5c3-4703-a3da-aaaf8984a503",
                    "name":"XM Test  Regression QA"
                },
                {
                    "id":"0bebb8ce-9dbc-49eb-bbc4-aacc7d699cad",
                    "name":"XM Test Automation Use ONLY"
                },
                {
                    "id":"38b07107-087f-4f31-b856-14e400fd0f8a",
                    "name":"XM Test Sushi Co"
                },
                {
                    "id":"0f0dd5a4-ce3d-4f7e-a039-326c34bf95e8",
                    "name":"XM Test Utopia Bagels"
                }
            ],
            "has_customization":false
        },
        {
            "item_number":"8001265",
            "name":"XM Test ReG(xm)",
            "object_type":"TRUCK_ITEM",
            "wonder_info":{
                "recipe_version_id":"800126501",
                "ingredient_id":null,
                "name":"ReG(xm)"
            },
            "related_wonder_infos":[

            ],
            "status":"BOM_CREATED",
            "restaurants":[
                {
                    "id":"0bebb8ce-9dbc-49eb-bbc4-aacc7d699cad",
                    "name":"XM Test Automation Use ONLY"
                },
                {
                    "id":"38b07107-087f-4f31-b856-14e400fd0f8a",
                    "name":"XM Test Sushi Co"
                },
                {
                    "id":"0f0dd5a4-ce3d-4f7e-a039-326c34bf95e8",
                    "name":"XM Test Utopia Bagels"
                }
            ],
            "has_customization":false
        },
        {
            "item_number":"8001146",
            "name":"Lemon Thyme Roasted Chicken, Family Style",
            "object_type":"TRUCK_ITEM",
            "wonder_info":{
                "recipe_version_id":"800114601",
                "ingredient_id":null,
                "name":"Lemon Thyme Roasted Chicken, Family Style"
            },
            "related_wonder_infos":[

            ],
            "status":"NEW",
            "restaurants":[
                {
                    "id":"0f0dd5a4-ce3d-4f7e-a039-326c34bf95e8",
                    "name":"XM Test Utopia Bagels"
                },
                {
                    "id":"60d96c30-a5c3-4703-a3da-aaaf8984a503",
                    "name":"XM Test  Regression QA"
                },
                {
                    "id":"019eb44c-354b-4c19-8101-342cd21ad254",
                    "name":"FS Comfort (COR Training)"
                },
                {
                    "id":"329d89fe-3247-46db-9ef0-8a51385ef33e",
                    "name":"The Regular"
                }
            ],
            "has_customization":false
        }
    ]
}
